examples/__init__.py
examples/ex10_list_of_primitives.py
examples/ex11_method_call.py
examples/ex12_method_call_slow.py
examples/ex13_success_error_callbacks.html
examples/ex13_success_error_callbacks.py
examples/ex14_event_trait.py
examples/ex15_embedding_in_qt.py
examples/ex16_template_person.html
examples/ex16_templating.js
examples/ex16_templating.py
examples/ex17_custom_angular_application.html
examples/ex17_custom_angular_application.py
examples/ex18_embedding_chaco.py
examples/ex19_embedding_mayavi.py
examples/ex1_simple_view.py
examples/ex20_mayavi_webgl_demo.html
examples/ex20_mayavi_webgl_demo.py
examples/ex21_matplotlib_web.py
examples/ex22_vuejs_demo.html
examples/ex22_vuejs_demo.py
examples/ex23_vuejs_web_demo.py
examples/ex2_simple_view_full.html
examples/ex2_simple_view_full_html.py
examples/ex3_simple_view_web.py
examples/ex4_simple_view_sans_traits.py
examples/ex5_user_resources.py
examples/ex6_model_updates.py
examples/ex7_model_updates_web.py
examples/ex8_instance_trait.py
examples/ex9_list_of_instances.py
examples/examples_notebook.ipynb
examples/ng_web.py
examples/web_async_example.py
examples/xtk.js
examples/ex5_data/Lena.png
examples/ex5_data/color_change.js
examples/ex5_data/colors.css
jigna/__init__.py
jigna/api.py
jigna/html_widget.py
jigna/qt.py
jigna/qt_server.py
jigna/server.py
jigna/template.py
jigna/vue_template.py
jigna/web_app.py
jigna/web_server.py
jigna/core/__init__.py
jigna/core/concurrent.py
jigna/core/interoperation.py
jigna/core/network_access.py
jigna/core/proxy_qwebview.py
jigna/core/wsgi.py
jigna/js/build.js
jigna/js/package.json
jigna/js/watcher.js
jigna/js/dist/jigna-vue.js
jigna/js/dist/jigna.js
jigna/js/src/app/async_client.js
jigna/js/src/app/async_proxy_factory.js
jigna/js/src/app/client.js
jigna/js/src/app/event_target.js
jigna/js/src/app/jigna-angular.js
jigna/js/src/app/jigna-vue.js
jigna/js/src/app/jigna.js
jigna/js/src/app/list_proxy.js
jigna-0.10.1.dist-info/DESCRIPTION.rst
jigna-0.10.1.dist-info/METADATA
jigna-0.10.1.dist-info/RECORD
jigna-0.10.1.dist-info/WHEEL
jigna-0.10.1.dist-info/metadata.json
jigna-0.10.1.dist-info/top_level.txt
