Metadata-Version: 2.0
Name: jigna
Version: 0.10.1
Summary: HTML frontend for Traits models.
Home-page: https://github.com/enthought/jigna
Author: Enthought, Inc
Author-email: info@enthought.com
License: BSD
Platform: UNKNOWN
Classifier: Development Status :: 4 - Beta
Classifier: Environment :: Web Environment
Classifier: Intended Audience :: Developers
Classifier: Intended Audience :: Science/Research
Classifier: License :: OSI Approved :: BSD License
Classifier: Operating System :: MacOS :: MacOS X
Classifier: Operating System :: Microsoft :: Windows
Classifier: Operating System :: OS Independent
Classifier: Operating System :: POSIX
Classifier: Operating System :: Unix
Classifier: Programming Language :: Python
Classifier: Programming Language :: JavaScript
Classifier: Topic :: Software Development
Classifier: Topic :: Software Development :: Libraries
Classifier: Topic :: Software Development :: User Interfaces
Requires-Dist: tornado
Requires-Dist: traits
Provides-Extra: pyside
Requires-Dist: pyside; extra == 'pyside'
Requires-Dist: tornado; extra == 'pyside'
Requires-Dist: traits; extra == 'pyside'
Provides-Extra: test
Requires-Dist: coverage; extra == 'test'
Requires-Dist: mock; extra == 'test'
Requires-Dist: nose; extra == 'test'
Requires-Dist: pyside; extra == 'test'
Requires-Dist: selenium; extra == 'test'
Requires-Dist: tornado; extra == 'test'
Requires-Dist: traits; extra == 'test'
